{
  "title-name": {
    "en": "Title Tracker",
    "es": "Nombre Tracker"
  },
  "title-label": {
    "en": "Show title",
    "es": "Mostrar nombre"
  },
  "year-label": {
    "en": "Show year",
    "es": "Mostrar año"
  },
  "days-label": {
    "en": "Show days names",
    "es": "Mostrar nombres de días"
  },
  "month-label": {
    "en": "Show month's name",
    "es": "Mostrar nombre del mes"
  },
  "date-label": {
    "en": "Year and Month",
    "es": "Año y mes"
  },
  "weekday-label": {
    "en": "First day of the week",
    "es": "Primer día de la semana"
  },
  "height-label": {
    "en": "Tracker's Height",
    "es": "Altura"
  },
  "weekdays-full": {
    "en": ["Monday", "Tuesday", "Wednesday", "Thursday", "Friday", "Saturday", "Sunday"],
    "es": ["Lunes", "Martes", "Miércoles", "Jueves", "Viernes", "Sábado", "Domingo"]
  },
  "weekdays": {
    "en": ["Mon", "Tue", "Wed", "Thu", "Fri", "Sat", "Sun"],
    "es": ["Lun", "Mar", "Mie", "Jue", "Vie", "Sab", "Dom"]
  },
  "color-label": {
    "en": "Transparency & Color",
    "es": "Transparencia & Color"
  },
  "column-label": {
    "en": "Columns",
    "es": "Columnas"
  },
  "row-label": {
    "en": "Rows",
    "es": "Filas"
  },
  "filling-label": {
    "en": "Fill your tracker",
    "es": "Llena el tracker"
  },
  "filling-day": {
    "en": "Day",
    "es": "Día"
  },
  "fonts-label": {
    "en": ["Title", "Month", "Year", "Days Name", "Days Numbers", "Goals" , "All"],
    "es": ["Nombre", "Mes", "Año", "Nombres días", "Números días", "Metas", "Todos"]
  },
  "tabs-names": {
    "en":  ["Components",
            "Background",
            "Days Shape", 
            "Goals",
            "Fonts",
            "Top Images",
            "Fill"],
    "es":  ["Componentes", "Fondo", "Forma de día", "Goals" ,"Fuentes", "Imágenes Arriba",  "Llenar"]
  },
  "download-button": {
    "en": "Download",
    "es": "Descargar"
  },
  "reset-button": {
    "en": "Reset",
    "es": "Resetear"
  },
  "edit-button": {
    "en": "Edit",
    "es": "Editar"
  },
  "upload-button": {
    "en": "Upload",
    "es": "Subir"
  },
  "upload-alert": {
    "en": "You can only upload a maximum of 2 images. Please delete one before uploading more.",
    "es": "Solo puede subir un máximo de 2 imágenes. Por favor, elimina una antes de subir más"
  },
  "config-button": {
    "en": "Download CONFIG",
    "es": "Descargar CONFIG"
  },
  "selected-label": {
    "en": "Selected",
    "es": "Seleccionada"
  },
  "top-images": {
    "en": "Amount of pictures",
    "es": "Cantidad de imágenes"
  },
  "navbar-language": {
    "en": "Language",
    "es": "Idioma"
  },
  "navbar-about": {
    "en": "About",
    "es": "Info"
  },
  "navbar-templates": {
    "en": "Templates",
    "es": "Plantillas"
  },
  "about-body": {
    "en": "Hello, I'm the creator of this page. I enjoy building web applications and sharing knowledge with the community.",
    "es": "Hola, soy el creador esta página. Disfruto creando aplicaciones web y compartiendo conocimientos con la comunidad."
  },
  "about-body2": {
    "en": "Feel free to make the trackers you need.",
    "es": "Se libre de hacer los trackers que quieras."
  },
  "error-h1": {
    "en": "Oops! Something went wrong.",
    "es": "Uups! Algo salió mal."
  },
  "error-p": {
    "en": "We're sorry, but the page you're looking for cannot be found or an error has occurred.",
    "es": "Lo sentimos, pero la página que estas buscando no se encuentra o un error ha ocurrido."
  }
}
